LICENSE
MANIFEST.in
README.md
setup.py
markup/Headings.py
markup/MarkdownPP.py
markup/Markers.py
markup/Module.py
markup/ObCanvas.py
markup/Processor.py
markup/Transform.py
markup/__init__.py
markup/headings.py
markup/main.py
markup/Modules/BlankLine.py
markup/Modules/EnvVariableReplacements.py
markup/Modules/Include.py
markup/Modules/IncludeCode.py
markup/Modules/IncludeURL.py
markup/Modules/IncludeWikilinkImage.py
markup/Modules/Reference.py
markup/Modules/SkipBlocks.py
markup/Modules/SkipHeaderMetadata.py
markup/Modules/SkipLine.py
markup/Modules/SkipObsidianComments.py
markup/Modules/TableOfContents.py
markup/Modules/WordPageBreak.py
markup/Modules/YoutubeEmbed.py
markup/Modules/__init__.py
markup_markdown.egg-info/PKG-INFO
markup_markdown.egg-info/SOURCES.txt
markup_markdown.egg-info/dependency_links.txt
markup_markdown.egg-info/entry_points.txt
markup_markdown.egg-info/requires.txt
markup_markdown.egg-info/top_level.txt
test/test.py