Metadata-Version: 1.1
Name: markup-markdown
Version: 1.5.8
Summary: Markup Markdown, Stack up markdown files with `!INCLUDE` directives.
Home-page: https://github.com/hailiang-wang/markup-markdown
Author: John Reese, Hai Liang W.
Author-email: hailiang.hl.wang@gmail.com
License: MIT License
Platform: UNKNOWN
Classifier: License :: OSI Approved :: MIT License
Classifier: Operating System :: OS Independent
Classifier: Programming Language :: Python
Classifier: Programming Language :: Python :: 3
Classifier: Programming Language :: Python :: 3.4
Classifier: Programming Language :: Python :: 3.5
Classifier: Programming Language :: Python :: 3.6
Classifier: Topic :: Utilities
Classifier: Development Status :: 5 - Production/Stable
